setup.py
acoustid_api/__init__.py
acoustid_api/api.py
acoustid_api/consts.py
acoustid_api/exceptions.py
python_acoustid_api.egg-info/PKG-INFO
python_acoustid_api.egg-info/SOURCES.txt
python_acoustid_api.egg-info/dependency_links.txt
python_acoustid_api.egg-info/requires.txt
python_acoustid_api.egg-info/top_level.txt