Metadata-Version: 1.1
Name: python-acoustid-api
Version: 0.0.1
Summary: Lightweight wrapper around AcoustID's API
Home-page: http://github.com/mattdennewitz/python-acoustid-api
Author: Matt Dennewitz
Author-email: mattdennewitz@gmail.com
License: UNKNOWN
Platform: UNKNOWN
Classifier: Development Status :: 2 - Pre-Alpha
Classifier: Intended Audience :: Developers
Classifier: License :: OSI Approved :: MIT License
Classifier: Programming Language :: Python
Classifier: Topic :: Multimedia :: Sound/Audio
Classifier: Topic :: Multimedia :: Sound/Audio :: Analysis
